mcp_domain_checker/__init__.py
mcp_domain_checker/__main__.py
mcp_domain_checker-1.0.5.dist-info/METADATA
mcp_domain_checker-1.0.5.dist-info/WHEEL
mcp_domain_checker-1.0.5.dist-info/entry_points.txt
mcp_domain_checker-1.0.5.dist-info/top_level.txt
mcp_domain_checker-1.0.5.dist-info/RECORD
